Metadata-Version: 2.1
Name: import-env-file
Version: 2020.7.1
Summary: import .env file environment variables into python
Home-page: https://github.com/andrewp-as-is/import-env-file.py
License: Unlicense
Keywords: env
Platform: UNKNOWN
Classifier: License :: Public Domain
Classifier: Operating System :: OS Independent
Classifier: Programming Language :: Python :: 3
